{
  "stage": "c0_18_deferred_bridge_latch_withdrawal_probe",
  "description": "Deferred-freeze bridge-latch test: arm under pure exact match, freeze the bridge-local latch only after arming, then withdraw the selector and test retention.",
  "rows": [
    {
      "run_id": "C018_clustered_composite_anchor_cycle_occupancy_latch",
      "family_id": "clustered_composite_anchor",
      "family_label": "Clustered composite anchor",
      "latch_id": "cycle_occupancy_latch",
      "latch_label": "Cycle occupancy latch",
      "armed_topology_class": "transfer_smeared",
      "post_withdrawal_topology_class": "transfer_smeared",
      "withdrawal_braid_dwell_time": 0.0,
      "loop_retention_score": 0.3105882663610634,
      "path_reuse_retention_score": 0.820205127526665,
      "latch_duty_cycle": 0.24163371612105997,
      "flow_concentration_index_post": 0.37725946857671705,
      "grade_exchange_coherence_post": 0.4302669486180108,
      "selector_off_recurrence_indicator": 0.9375,
      "locking_label": "no_locking_after_withdrawal",
      "notes": ""
    },
    {
      "run_id": "C018_clustered_composite_anchor_edge_path_reuse_latch",
      "family_id": "clustered_composite_anchor",
      "family_label": "Clustered composite anchor",
      "latch_id": "edge_path_reuse_latch",
      "latch_label": "Edge-path reuse latch",
      "armed_topology_class": "transfer_smeared",
      "post_withdrawal_topology_class": "transfer_smeared",
      "withdrawal_braid_dwell_time": 0.0,
      "loop_retention_score": 0.5774785003040459,
      "path_reuse_retention_score": 1.025230788262056,
      "latch_duty_cycle": 0.1634664381526709,
      "flow_concentration_index_post": 0.4737390298529181,
      "grade_exchange_coherence_post": 0.5051182664238933,
      "selector_off_recurrence_indicator": 0.96875,
      "locking_label": "no_locking_after_withdrawal",
      "notes": ""
    },
    {
      "run_id": "C018_clustered_composite_anchor_combined_cycle_path_latch",
      "family_id": "clustered_composite_anchor",
      "family_label": "Clustered composite anchor",
      "latch_id": "combined_cycle_path_latch",
      "latch_label": "Combined cycle-plus-path latch",
      "armed_topology_class": "transfer_smeared",
      "post_withdrawal_topology_class": "transfer_smeared",
      "withdrawal_braid_dwell_time": 0.0,
      "loop_retention_score": 0.4511978386500845,
      "path_reuse_retention_score": 1.1027673208786863,
      "latch_duty_cycle": 0.14361613722443717,
      "flow_concentration_index_post": 0.5177553052945301,
      "grade_exchange_coherence_post": 0.4393810490780934,
      "selector_off_recurrence_indicator": 0.9375,
      "locking_label": "no_locking_after_withdrawal",
      "notes": ""
    },
    {
      "run_id": "C018_counter_propagating_corridor_cycle_occupancy_latch",
      "family_id": "counter_propagating_corridor",
      "family_label": "Counter-propagating corridor",
      "latch_id": "cycle_occupancy_latch",
      "latch_label": "Cycle occupancy latch",
      "armed_topology_class": "unresolved_mixed",
      "post_withdrawal_topology_class": "unresolved_mixed",
      "withdrawal_braid_dwell_time": 0.0,
      "loop_retention_score": 2.0494422675945847,
      "path_reuse_retention_score": 1.1051976538543555,
      "latch_duty_cycle": 0.20520018250068603,
      "flow_concentration_index_post": 0.34539783644589067,
      "grade_exchange_coherence_post": 0.5299430573202397,
      "selector_off_recurrence_indicator": 0.0,
      "locking_label": "no_locking_after_withdrawal",
      "notes": ""
    },
    {
      "run_id": "C018_counter_propagating_corridor_edge_path_reuse_latch",
      "family_id": "counter_propagating_corridor",
      "family_label": "Counter-propagating corridor",
      "latch_id": "edge_path_reuse_latch",
      "latch_label": "Edge-path reuse latch",
      "armed_topology_class": "unresolved_mixed",
      "post_withdrawal_topology_class": "unresolved_mixed",
      "withdrawal_braid_dwell_time": 0.0,
      "loop_retention_score": 5.886424310828654,
      "path_reuse_retention_score": 1.0725458151922167,
      "latch_duty_cycle": 0.20792894390795946,
      "flow_concentration_index_post": 0.3351155003650285,
      "grade_exchange_coherence_post": 0.4573129909452768,
      "selector_off_recurrence_indicator": 0.0,
      "locking_label": "no_locking_after_withdrawal",
      "notes": ""
    },
    {
      "run_id": "C018_counter_propagating_corridor_combined_cycle_path_latch",
      "family_id": "counter_propagating_corridor",
      "family_label": "Counter-propagating corridor",
      "latch_id": "combined_cycle_path_latch",
      "latch_label": "Combined cycle-plus-path latch",
      "armed_topology_class": "unresolved_mixed",
      "post_withdrawal_topology_class": "unresolved_mixed",
      "withdrawal_braid_dwell_time": 0.0,
      "loop_retention_score": 7.357865105792483,
      "path_reuse_retention_score": 1.050006168505575,
      "latch_duty_cycle": 0.2012404084532615,
      "flow_concentration_index_post": 0.3305416197760043,
      "grade_exchange_coherence_post": 0.4637699676688641,
      "selector_off_recurrence_indicator": 0.0,
      "locking_label": "no_locking_after_withdrawal",
      "notes": ""
    },
    {
      "run_id": "C018_phase_ordered_symmetric_triad_cycle_occupancy_latch",
      "family_id": "phase_ordered_symmetric_triad",
      "family_label": "Phase-ordered symmetric triad",
      "latch_id": "cycle_occupancy_latch",
      "latch_label": "Cycle occupancy latch",
      "armed_topology_class": "transfer_smeared",
      "post_withdrawal_topology_class": "transfer_smeared",
      "withdrawal_braid_dwell_time": 0.0,
      "loop_retention_score": 0.12406999356807562,
      "path_reuse_retention_score": 0.9947467728523217,
      "latch_duty_cycle": 0.4694724719399127,
      "flow_concentration_index_post": 0.3177615791947938,
      "grade_exchange_coherence_post": 0.6449360836957523,
      "selector_off_recurrence_indicator": 0.0,
      "locking_label": "no_locking_after_withdrawal",
      "notes": ""
    },
    {
      "run_id": "C018_phase_ordered_symmetric_triad_edge_path_reuse_latch",
      "family_id": "phase_ordered_symmetric_triad",
      "family_label": "Phase-ordered symmetric triad",
      "latch_id": "edge_path_reuse_latch",
      "latch_label": "Edge-path reuse latch",
      "armed_topology_class": "transfer_smeared",
      "post_withdrawal_topology_class": "transfer_smeared",
      "withdrawal_braid_dwell_time": 0.0,
      "loop_retention_score": 0.8652245505259236,
      "path_reuse_retention_score": 0.98092127165004,
      "latch_duty_cycle": 0.14392916376466108,
      "flow_concentration_index_post": 0.3146192134581225,
      "grade_exchange_coherence_post": 0.7084565102206204,
      "selector_off_recurrence_indicator": 0.0,
      "locking_label": "no_locking_after_withdrawal",
      "notes": ""
    },
    {
      "run_id": "C018_phase_ordered_symmetric_triad_combined_cycle_path_latch",
      "family_id": "phase_ordered_symmetric_triad",
      "family_label": "Phase-ordered symmetric triad",
      "latch_id": "combined_cycle_path_latch",
      "latch_label": "Combined cycle-plus-path latch",
      "armed_topology_class": "transfer_smeared",
      "post_withdrawal_topology_class": "transfer_smeared",
      "withdrawal_braid_dwell_time": 0.0,
      "loop_retention_score": 1.250250232295316,
      "path_reuse_retention_score": 0.9580438799513976,
      "latch_duty_cycle": 0.13581795357167578,
      "flow_concentration_index_post": 0.31478570761795843,
      "grade_exchange_coherence_post": 0.5137318339250652,
      "selector_off_recurrence_indicator": 0.0,
      "locking_label": "no_locking_after_withdrawal",
      "notes": ""
    }
  ]
}